<?xml version="1.0" encoding="UTF-8"?>
<QCARConfig xmlns:xsi="http://www.w3.org/2001/XMLSchema-instance" xsi:noNamespaceSchemaLocation="qcar_config.xsd">
  <Tracking>
    <ImageTarget name="ClearCard" size="1.000000 1.415045" />
    <ImageTarget name="VisualizationCardv24" size="0.700000 0.990532" />
    <ImageTarget name="VisualizationCard3" size="0.700000 0.990532" />
    <ImageTarget name="VisualizationCard2" size="0.700000 0.990532" />
    <ImageTarget name="datasetsummary" size="0.700000 0.990532" />
    <ImageTarget name="changecard" size="0.700000 0.990532" />
    <ImageTarget name="VisualizationCardv2" size="1.000000 1.415045" />
    <ImageTarget name="VisualizationCard" size="1.000000 1.415045" />
    <ImageTarget name="SelectDataset" size="1.000000 1.415045" />
    <ImageTarget name="SaveCard" size="1.000000 1.415045" />
    <ImageTarget name="LoadCard" size="1.000000 1.415045" />
    <ImageTarget name="FilterCard" size="1.000000 1.415045" />
    <ImageTarget name="AxisCard" size="1.000000 1.415045" />
  </Tracking>
</QCARConfig>
